pricegenerator/PriceGenerator.py
pricegenerator/UniLogger.py
pricegenerator/__init__.py
pricegenerator/__main__.py
pricegenerator/google_template_example.j2
pricegenerator-1.4.93.dist-info/LICENSE
pricegenerator-1.4.93.dist-info/METADATA
pricegenerator-1.4.93.dist-info/WHEEL
pricegenerator-1.4.93.dist-info/entry_points.txt
pricegenerator-1.4.93.dist-info/top_level.txt
pricegenerator-1.4.93.dist-info/zip-safe
pricegenerator-1.4.93.dist-info/RECORD
