Metadata-Version: 2.1
Name: pricegenerator
Version: 1.4.93
Summary: PriceGenerator is the platform for generating prices similar to real stock prices, but you can control the statistics of their distribution. Generates chain of candlesticks with predefined statistical parameters, return Pandas DataFrame or saving as .CSV-file with OHLCV-candlestick in every string. Use PriceGenerator to generate synthetic data to test your trading strategy.
Home-page: https://github.com/Tim55667757/PriceGenerator/
Author: Timur Gilmullin
Author-email: tim55667757@gmail.com
License: Apache-2.0
Download-URL: https://github.com/Tim55667757/PriceGenerator.git
Keywords: history,csv,stock,forex,prices,candlesticks,parser,generator,statistics,testing,testdata,OHLCV,generator
Platform: UNKNOWN
Classifier: Development Status :: 5 - Production/Stable
Classifier: Environment :: Console
Classifier: Intended Audience :: Financial and Insurance Industry
Classifier: Topic :: Utilities
Classifier: License :: OSI Approved :: Apache Software License
Classifier: Natural Language :: English
Classifier: Programming Language :: Python :: 3
License-File: LICENSE
Requires-Dist: requests (>=2.25.1)
Requires-Dist: pandas (>=1.5.2)
Requires-Dist: bokeh (>=3.0.3)
Requires-Dist: bkcharts (>=0.2)
Requires-Dist: numpy (>=1.23.5)
Requires-Dist: matplotlib (>=3.3.4)
Requires-Dist: python-dateutil (>=2.8.1)
Requires-Dist: jinja2 (>=2.11.3)
Requires-Dist: pandas-ta (>=0.2.45b0)
Requires-Dist: notebook (>=6.5.2)
